knowledge_verificator/__init__.py
knowledge_verificator/answer_chooser.py
knowledge_verificator/backend.py
knowledge_verificator/command_line.py
knowledge_verificator/io_handler.py
knowledge_verificator/main.py
knowledge_verificator/materials.py
knowledge_verificator/nli.py
knowledge_verificator/qg/__init__.py
knowledge_verificator/qg/base.py
knowledge_verificator/qg/qg_model_factory.py
knowledge_verificator/qg/t5.py
knowledge_verificator/utils/configuration_parser.py
knowledge_verificator/utils/filesystem.py
knowledge_verificator/utils/menu.py
knowledge_verificator/utils/string.py
knowledge_verificator-0.1.3.dist-info/LICENSE
knowledge_verificator-0.1.3.dist-info/METADATA
knowledge_verificator-0.1.3.dist-info/WHEEL
knowledge_verificator-0.1.3.dist-info/RECORD
