Metadata-Version: 2.1
Name: knowledge-verificator
Version: 0.1.3
Summary: User's knowledge verificator
Author: Igor Sosnowicz
Author-email: igor@sosnowicz.eu
Requires-Python: >=3.12,<4.0
Classifier: Programming Language :: Python :: 3
Classifier: Programming Language :: Python :: 3.12
Requires-Dist: fastapi[standard] (>=0.115.2,<0.116.0)
Requires-Dist: nltk (>=3.9.1,<4.0.0)
Requires-Dist: protobuf (>=5.28.2,<6.0.0)
Requires-Dist: pyyaml (>=6.0.2,<7.0.0)
Requires-Dist: requests (>=2.32.3,<3.0.0)
Requires-Dist: rich (>=13.8.1,<14.0.0)
Requires-Dist: sentence-transformers (>=3.1.1,<4.0.0)
Requires-Dist: sentencepiece (>=0.2.0,<0.3.0)
Requires-Dist: torch (>=2.4.1,<3.0.0)
Requires-Dist: tqdm (>=4.66.5,<5.0.0)
Requires-Dist: transformers (>=4.44.2,<5.0.0)
